aidge_model_explorer/__init__.py
aidge_model_explorer/config.py
aidge_model_explorer/consts.py
aidge_model_explorer/main.py
aidge_model_explorer/visualize.py
aidge_model_explorer/converters/__init__.py
aidge_model_explorer/converters/onnx_converter.py
aidge_model_explorer/converters/runtime_converter.py
aidge_model_explorer-0.0.1.dist-info/METADATA
aidge_model_explorer-0.0.1.dist-info/WHEEL
aidge_model_explorer-0.0.1.dist-info/top_level.txt
aidge_model_explorer-0.0.1.dist-info/RECORD
