Metadata-Version: 2.4
Name: aidge_model_explorer
Version: 0.0.1
Summary: Aidge module for model explorer: https://github.com/google-ai-edge/model-explorer.
Project-URL: Homepage, https://www.deepgreen.ai/en/platform
Project-URL: Documentation, https://eclipse.dev/aidge/
Project-URL: Repository, https://gitlab.eclipse.org/eclipse/aidge/aidge_model_explorer
Project-URL: Issues, https://gitlab.eclipse.org/eclipse/aidge/aidge_model_explorer/-/issues/
Project-URL: Changelog, https://gitlab.eclipse.org/eclipse/aidge/aidge_model_explorer/-/releases
Classifier: Development Status :: 2 - Pre-Alpha
Classifier: Programming Language :: Python :: 3
Requires-Python: >=3.10
Requires-Dist: ai-edge-model-explorer
Provides-Extra: test
Requires-Dist: pytest; extra == "test"
